{
  "version": "6",
  "dialect": "sqlite",
  "id": "6e49038e-14d8-44d5-a8cf-7362a820d8ae",
  "prevId": "c1a2b3d4-e5f6-7890-abcd-ef1234567890",
  "tables": {
    "airbnb_payout_items": {
      "name": "airbnb_payout_items",
      "columns": {
        "id": {
          "name": "id",
          "type": "integer",
          "primaryKey": true,
          "notNull": true,
          "autoincrement": false
        },
        "payout_id": {
          "name": "payout_id",
          "type": "integer",
          "primaryKey": false,
          "notNull": true,
          "autoincrement": false
        },
        "confirmation_code": {
          "name": "confirmation_code",
          "type": "text",
          "primaryKey": false,
          "notNull": true,
          "autoincrement": false
        },
        "guest_name": {
          "name": "guest_name",
          "type": "text",
          "primaryKey": false,
          "notNull": false,
          "autoincrement": false
        },
        "amount_minor": {
          "name": "amount_minor",
          "type": "integer",
          "primaryKey": false,
          "notNull": true,
          "autoincrement": false
        },
        "date_range_start": {
          "name": "date_range_start",
          "type": "text",
          "primaryKey": false,
          "notNull": false,
          "autoincrement": false
        },
        "date_range_end": {
          "name": "date_range_end",
          "type": "text",
          "primaryKey": false,
          "notNull": false,
          "autoincrement": false
        },
        "listing_id": {
          "name": "listing_id",
          "type": "text",
          "primaryKey": false,
          "notNull": false,
          "autoincrement": false
        },
        "listing_name": {
          "name": "listing_name",
          "type": "text",
          "primaryKey": false,
          "notNull": false,
          "autoincrement": false
        },
        "created_at": {
          "name": "created_at",
          "type": "text",
          "primaryKey": false,
          "notNull": true,
          "autoincrement": false,
          "default": "(datetime('now'))"
        }
      },
      "indexes": {
        "idx_payitem_code": {
          "name": "idx_payitem_code",
          "columns": [
            "confirmation_code"
          ],
          "isUnique": false
        }
      },
      "foreignKeys": {
        "airbnb_payout_items_payout_id_airbnb_payouts_id_fk": {
          "name": "airbnb_payout_items_payout_id_airbnb_payouts_id_fk",
          "tableFrom": "airbnb_payout_items",
          "tableTo": "airbnb_payouts",
          "columnsFrom": [
            "payout_id"
          ],
          "columnsTo": [
            "id"
          ],
          "onDelete": "cascade",
          "onUpdate": "no action"
        }
      },
      "compositePrimaryKeys": {},
      "uniqueConstraints": {},
      "checkConstraints": {}
    },
    "airbnb_payouts": {
      "name": "airbnb_payouts",
      "columns": {
        "id": {
          "name": "id",
          "type": "integer",
          "primaryKey": true,
          "notNull": true,
          "autoincrement": false
        },
        "user_id": {
          "name": "user_id",
          "type": "integer",
          "primaryKey": false,
          "notNull": true,
          "autoincrement": false
        },
        "external_ref": {
          "name": "external_ref",
          "type": "text",
          "primaryKey": false,
          "notNull": true,
          "autoincrement": false
        },
        "currency": {
          "name": "currency",
          "type": "text",
          "primaryKey": false,
          "notNull": true,
          "autoincrement": false,
          "default": "'PHP'"
        },
        "payout_total_minor": {
          "name": "payout_total_minor",
          "type": "integer",
          "primaryKey": false,
          "notNull": true,
          "autoincrement": false
        },
        "sent_date": {
          "name": "sent_date",
          "type": "text",
          "primaryKey": false,
          "notNull": false,
          "autoincrement": false
        },
        "expected_arrival_date": {
          "name": "expected_arrival_date",
          "type": "text",
          "primaryKey": false,
          "notNull": false,
          "autoincrement": false
        },
        "bank_account_label": {
          "name": "bank_account_label",
          "type": "text",
          "primaryKey": false,
          "notNull": false,
          "autoincrement": false
        },
        "airbnb_account_id": {
          "name": "airbnb_account_id",
          "type": "text",
          "primaryKey": false,
          "notNull": false,
          "autoincrement": false
        },
        "source_log_entry_id": {
          "name": "source_log_entry_id",
          "type": "integer",
          "primaryKey": false,
          "notNull": false,
          "autoincrement": false
        },
        "cashflow_transaction_id": {
          "name": "cashflow_transaction_id",
          "type": "integer",
          "primaryKey": false,
          "notNull": false,
          "autoincrement": false
        },
        "created_at": {
          "name": "created_at",
          "type": "text",
          "primaryKey": false,
          "notNull": true,
          "autoincrement": false,
          "default": "(datetime('now'))"
        },
        "updated_at": {
          "name": "updated_at",
          "type": "text",
          "primaryKey": false,
          "notNull": true,
          "autoincrement": false,
          "default": "(datetime('now'))"
        }
      },
      "indexes": {
        "uq_payout_user_ref": {
          "name": "uq_payout_user_ref",
          "columns": [
            "user_id",
            "external_ref"
          ],
          "isUnique": true
        }
      },
      "foreignKeys": {
        "airbnb_payouts_user_id_users_id_fk": {
          "name": "airbnb_payouts_user_id_users_id_fk",
          "tableFrom": "airbnb_payouts",
          "tableTo": "users",
          "columnsFrom": [
            "user_id"
          ],
          "columnsTo": [
            "id"
          ],
          "onDelete": "no action",
          "onUpdate": "no action"
        },
        "airbnb_payouts_source_log_entry_id_log_entries_id_fk": {
          "name": "airbnb_payouts_source_log_entry_id_log_entries_id_fk",
          "tableFrom": "airbnb_payouts",
          "tableTo": "log_entries",
          "columnsFrom": [
            "source_log_entry_id"
          ],
          "columnsTo": [
            "id"
          ],
          "onDelete": "no action",
          "onUpdate": "no action"
        },
        "airbnb_payouts_cashflow_transaction_id_transactions_id_fk": {
          "name": "airbnb_payouts_cashflow_transaction_id_transactions_id_fk",
          "tableFrom": "airbnb_payouts",
          "tableTo": "transactions",
          "columnsFrom": [
            "cashflow_transaction_id"
          ],
          "columnsTo": [
            "id"
          ],
          "onDelete": "no action",
          "onUpdate": "no action"
        }
      },
      "compositePrimaryKeys": {},
      "uniqueConstraints": {},
      "checkConstraints": {}
    },
    "airbnb_reservations": {
      "name": "airbnb_reservations",
      "columns": {
        "id": {
          "name": "id",
          "type": "integer",
          "primaryKey": true,
          "notNull": true,
          "autoincrement": false
        },
        "user_id": {
          "name": "user_id",
          "type": "integer",
          "primaryKey": false,
          "notNull": true,
          "autoincrement": false
        },
        "confirmation_code": {
          "name": "confirmation_code",
          "type": "text",
          "primaryKey": false,
          "notNull": true,
          "autoincrement": false
        },
        "listing_id": {
          "name": "listing_id",
          "type": "text",
          "primaryKey": false,
          "notNull": false,
          "autoincrement": false
        },
        "listing_name": {
          "name": "listing_name",
          "type": "text",
          "primaryKey": false,
          "notNull": false,
          "autoincrement": false
        },
        "guest_name": {
          "name": "guest_name",
          "type": "text",
          "primaryKey": false,
          "notNull": false,
          "autoincrement": false
        },
        "check_in": {
          "name": "check_in",
          "type": "text",
          "primaryKey": false,
          "notNull": false,
          "autoincrement": false
        },
        "check_out": {
          "name": "check_out",
          "type": "text",
          "primaryKey": false,
          "notNull": false,
          "autoincrement": false
        },
        "nights": {
          "name": "nights",
          "type": "integer",
          "primaryKey": false,
          "notNull": false,
          "autoincrement": false
        },
        "guests_count": {
          "name": "guests_count",
          "type": "integer",
          "primaryKey": false,
          "notNull": false,
          "autoincrement": false
        },
        "status": {
          "name": "status",
          "type": "text",
          "primaryKey": false,
          "notNull": true,
          "autoincrement": false,
          "default": "'confirmed'"
        },
        "currency": {
          "name": "currency",
          "type": "text",
          "primaryKey": false,
          "notNull": true,
          "autoincrement": false,
          "default": "'PHP'"
        },
        "gross_total_minor": {
          "name": "gross_total_minor",
          "type": "integer",
          "primaryKey": false,
          "notNull": false,
          "autoincrement": false
        },
        "cleaning_fee_minor": {
          "name": "cleaning_fee_minor",
          "type": "integer",
          "primaryKey": false,
          "notNull": false,
          "autoincrement": false
        },
        "host_service_fee_minor": {
          "name": "host_service_fee_minor",
          "type": "integer",
          "primaryKey": false,
          "notNull": false,
          "autoincrement": false
        },
        "projected_earning_minor": {
          "name": "projected_earning_minor",
          "type": "integer",
          "primaryKey": false,
          "notNull": false,
          "autoincrement": false
        },
        "realized_earning_minor": {
          "name": "realized_earning_minor",
          "type": "integer",
          "primaryKey": false,
          "notNull": false,
          "autoincrement": false
        },
        "source_log_entry_id": {
          "name": "source_log_entry_id",
          "type": "integer",
          "primaryKey": false,
          "notNull": false,
          "autoincrement": false
        },
        "created_at": {
          "name": "created_at",
          "type": "text",
          "primaryKey": false,
          "notNull": true,
          "autoincrement": false,
          "default": "(datetime('now'))"
        },
        "updated_at": {
          "name": "updated_at",
          "type": "text",
          "primaryKey": false,
          "notNull": true,
          "autoincrement": false,
          "default": "(datetime('now'))"
        }
      },
      "indexes": {
        "uq_resv_user_code": {
          "name": "uq_resv_user_code",
          "columns": [
            "user_id",
            "confirmation_code"
          ],
          "isUnique": true
        },
        "idx_resv_user_status": {
          "name": "idx_resv_user_status",
          "columns": [
            "user_id",
            "status",
            "check_in"
          ],
          "isUnique": false
        }
      },
      "foreignKeys": {
        "airbnb_reservations_user_id_users_id_fk": {
          "name": "airbnb_reservations_user_id_users_id_fk",
          "tableFrom": "airbnb_reservations",
          "tableTo": "users",
          "columnsFrom": [
            "user_id"
          ],
          "columnsTo": [
            "id"
          ],
          "onDelete": "no action",
          "onUpdate": "no action"
        },
        "airbnb_reservations_source_log_entry_id_log_entries_id_fk": {
          "name": "airbnb_reservations_source_log_entry_id_log_entries_id_fk",
          "tableFrom": "airbnb_reservations",
          "tableTo": "log_entries",
          "columnsFrom": [
            "source_log_entry_id"
          ],
          "columnsTo": [
            "id"
          ],
          "onDelete": "no action",
          "onUpdate": "no action"
        }
      },
      "compositePrimaryKeys": {},
      "uniqueConstraints": {},
      "checkConstraints": {
        "chk_resv_status": {
          "name": "chk_resv_status",
          "value": "status IN ('confirmed','canceled','paid_out')"
        }
      }
    },
    "app_settings": {
      "name": "app_settings",
      "columns": {
        "user_id": {
          "name": "user_id",
          "type": "integer",
          "primaryKey": false,
          "notNull": true,
          "autoincrement": false
        },
        "key": {
          "name": "key",
          "type": "text",
          "primaryKey": false,
          "notNull": true,
          "autoincrement": false
        },
        "value": {
          "name": "value",
          "type": "text",
          "primaryKey": false,
          "notNull": true,
          "autoincrement": false
        },
        "updated_at": {
          "name": "updated_at",
          "type": "text",
          "primaryKey": false,
          "notNull": true,
          "autoincrement": false,
          "default": "(datetime('now'))"
        }
      },
      "indexes": {},
      "foreignKeys": {
        "app_settings_user_id_users_id_fk": {
          "name": "app_settings_user_id_users_id_fk",
          "tableFrom": "app_settings",
          "tableTo": "users",
          "columnsFrom": [
            "user_id"
          ],
          "columnsTo": [
            "id"
          ],
          "onDelete": "no action",
          "onUpdate": "no action"
        }
      },
      "compositePrimaryKeys": {
        "app_settings_user_id_key_pk": {
          "columns": [
            "user_id",
            "key"
          ],
          "name": "app_settings_user_id_key_pk"
        }
      },
      "uniqueConstraints": {},
      "checkConstraints": {}
    },
    "audit_log": {
      "name": "audit_log",
      "columns": {
        "id": {
          "name": "id",
          "type": "integer",
          "primaryKey": true,
          "notNull": true,
          "autoincrement": false
        },
        "user_id": {
          "name": "user_id",
          "type": "integer",
          "primaryKey": false,
          "notNull": false,
          "autoincrement": false
        },
        "actor": {
          "name": "actor",
          "type": "text",
          "primaryKey": false,
          "notNull": true,
          "autoincrement": false
        },
        "action": {
          "name": "action",
          "type": "text",
          "primaryKey": false,
          "notNull": true,
          "autoincrement": false
        },
        "entity": {
          "name": "entity",
          "type": "text",
          "primaryKey": false,
          "notNull": true,
          "autoincrement": false
        },
        "entity_id": {
          "name": "entity_id",
          "type": "text",
          "primaryKey": false,
          "notNull": false,
          "autoincrement": false
        },
        "payload_json": {
          "name": "payload_json",
          "type": "text",
          "primaryKey": false,
          "notNull": false,
          "autoincrement": false
        },
        "ip_address": {
          "name": "ip_address",
          "type": "text",
          "primaryKey": false,
          "notNull": false,
          "autoincrement": false
        },
        "user_agent": {
          "name": "user_agent",
          "type": "text",
          "primaryKey": false,
          "notNull": false,
          "autoincrement": false
        },
        "created_at": {
          "name": "created_at",
          "type": "text",
          "primaryKey": false,
          "notNull": true,
          "autoincrement": false,
          "default": "(datetime('now'))"
        }
      },
      "indexes": {
        "idx_audit_user_time": {
          "name": "idx_audit_user_time",
          "columns": [
            "user_id",
            "created_at"
          ],
          "isUnique": false
        }
      },
      "foreignKeys": {
        "audit_log_user_id_users_id_fk": {
          "name": "audit_log_user_id_users_id_fk",
          "tableFrom": "audit_log",
          "tableTo": "users",
          "columnsFrom": [
            "user_id"
          ],
          "columnsTo": [
            "id"
          ],
          "onDelete": "no action",
          "onUpdate": "no action"
        }
      },
      "compositePrimaryKeys": {},
      "uniqueConstraints": {},
      "checkConstraints": {
        "chk_audit_actor": {
          "name": "chk_audit_actor",
          "value": "actor = 'user' OR actor = 'anon' OR actor = 'system' OR actor LIKE 'system:_%' OR actor LIKE 'agent:%/%' OR actor LIKE 'platform:_%'"
        }
      }
    },
    "categories": {
      "name": "categories",
      "columns": {
        "id": {
          "name": "id",
          "type": "integer",
          "primaryKey": true,
          "notNull": true,
          "autoincrement": false
        },
        "user_id": {
          "name": "user_id",
          "type": "integer",
          "primaryKey": false,
          "notNull": true,
          "autoincrement": false
        },
        "name": {
          "name": "name",
          "type": "text",
          "primaryKey": false,
          "notNull": true,
          "autoincrement": false
        },
        "kind": {
          "name": "kind",
          "type": "text",
          "primaryKey": false,
          "notNull": true,
          "autoincrement": false
        },
        "created_at": {
          "name": "created_at",
          "type": "text",
          "primaryKey": false,
          "notNull": true,
          "autoincrement": false,
          "default": "(datetime('now'))"
        }
      },
      "indexes": {
        "uq_categories_user_name": {
          "name": "uq_categories_user_name",
          "columns": [
            "user_id",
            "name"
          ],
          "isUnique": true
        }
      },
      "foreignKeys": {
        "categories_user_id_users_id_fk": {
          "name": "categories_user_id_users_id_fk",
          "tableFrom": "categories",
          "tableTo": "users",
          "columnsFrom": [
            "user_id"
          ],
          "columnsTo": [
            "id"
          ],
          "onDelete": "no action",
          "onUpdate": "no action"
        }
      },
      "compositePrimaryKeys": {},
      "uniqueConstraints": {},
      "checkConstraints": {}
    },
    "log_entries": {
      "name": "log_entries",
      "columns": {
        "id": {
          "name": "id",
          "type": "integer",
          "primaryKey": true,
          "notNull": true,
          "autoincrement": false
        },
        "user_id": {
          "name": "user_id",
          "type": "integer",
          "primaryKey": false,
          "notNull": true,
          "autoincrement": false
        },
        "source": {
          "name": "source",
          "type": "text",
          "primaryKey": false,
          "notNull": true,
          "autoincrement": false,
          "default": "'email'"
        },
        "source_account": {
          "name": "source_account",
          "type": "text",
          "primaryKey": false,
          "notNull": true,
          "autoincrement": false
        },
        "external_ref": {
          "name": "external_ref",
          "type": "text",
          "primaryKey": false,
          "notNull": true,
          "autoincrement": false
        },
        "sender": {
          "name": "sender",
          "type": "text",
          "primaryKey": false,
          "notNull": true,
          "autoincrement": false
        },
        "subject": {
          "name": "subject",
          "type": "text",
          "primaryKey": false,
          "notNull": false,
          "autoincrement": false
        },
        "received_at": {
          "name": "received_at",
          "type": "text",
          "primaryKey": false,
          "notNull": true,
          "autoincrement": false
        },
        "dkim_pass": {
          "name": "dkim_pass",
          "type": "integer",
          "primaryKey": false,
          "notNull": true,
          "autoincrement": false,
          "default": 0
        },
        "kind": {
          "name": "kind",
          "type": "text",
          "primaryKey": false,
          "notNull": true,
          "autoincrement": false,
          "default": "'unknown'"
        },
        "parser_version": {
          "name": "parser_version",
          "type": "text",
          "primaryKey": false,
          "notNull": false,
          "autoincrement": false
        },
        "parsed_json": {
          "name": "parsed_json",
          "type": "text",
          "primaryKey": false,
          "notNull": false,
          "autoincrement": false
        },
        "status": {
          "name": "status",
          "type": "text",
          "primaryKey": false,
          "notNull": true,
          "autoincrement": false,
          "default": "'pending'"
        },
        "status_reason": {
          "name": "status_reason",
          "type": "text",
          "primaryKey": false,
          "notNull": false,
          "autoincrement": false
        },
        "created_at": {
          "name": "created_at",
          "type": "text",
          "primaryKey": false,
          "notNull": true,
          "autoincrement": false,
          "default": "(datetime('now'))"
        },
        "updated_at": {
          "name": "updated_at",
          "type": "text",
          "primaryKey": false,
          "notNull": true,
          "autoincrement": false,
          "default": "(datetime('now'))"
        }
      },
      "indexes": {
        "uq_log_entry_user_source_ref": {
          "name": "uq_log_entry_user_source_ref",
          "columns": [
            "user_id",
            "source",
            "external_ref"
          ],
          "isUnique": true
        },
        "idx_log_user_status": {
          "name": "idx_log_user_status",
          "columns": [
            "user_id",
            "status",
            "received_at"
          ],
          "isUnique": false
        },
        "idx_log_user_kind": {
          "name": "idx_log_user_kind",
          "columns": [
            "user_id",
            "kind",
            "received_at"
          ],
          "isUnique": false
        }
      },
      "foreignKeys": {
        "log_entries_user_id_users_id_fk": {
          "name": "log_entries_user_id_users_id_fk",
          "tableFrom": "log_entries",
          "tableTo": "users",
          "columnsFrom": [
            "user_id"
          ],
          "columnsTo": [
            "id"
          ],
          "onDelete": "no action",
          "onUpdate": "no action"
        }
      },
      "compositePrimaryKeys": {},
      "uniqueConstraints": {},
      "checkConstraints": {
        "chk_log_status": {
          "name": "chk_log_status",
          "value": "status IN ('pending','recorded','rejected','parse_failed')"
        }
      }
    },
    "log_raw": {
      "name": "log_raw",
      "columns": {
        "log_entry_id": {
          "name": "log_entry_id",
          "type": "integer",
          "primaryKey": true,
          "notNull": true,
          "autoincrement": false
        },
        "headers_json": {
          "name": "headers_json",
          "type": "text",
          "primaryKey": false,
          "notNull": false,
          "autoincrement": false
        },
        "body_text": {
          "name": "body_text",
          "type": "text",
          "primaryKey": false,
          "notNull": false,
          "autoincrement": false
        },
        "body_html": {
          "name": "body_html",
          "type": "text",
          "primaryKey": false,
          "notNull": false,
          "autoincrement": false
        }
      },
      "indexes": {},
      "foreignKeys": {
        "log_raw_log_entry_id_log_entries_id_fk": {
          "name": "log_raw_log_entry_id_log_entries_id_fk",
          "tableFrom": "log_raw",
          "tableTo": "log_entries",
          "columnsFrom": [
            "log_entry_id"
          ],
          "columnsTo": [
            "id"
          ],
          "onDelete": "cascade",
          "onUpdate": "no action"
        }
      },
      "compositePrimaryKeys": {},
      "uniqueConstraints": {},
      "checkConstraints": {}
    },
    "log_rules": {
      "name": "log_rules",
      "columns": {
        "id": {
          "name": "id",
          "type": "integer",
          "primaryKey": true,
          "notNull": true,
          "autoincrement": false
        },
        "user_id": {
          "name": "user_id",
          "type": "integer",
          "primaryKey": false,
          "notNull": true,
          "autoincrement": false
        },
        "source": {
          "name": "source",
          "type": "text",
          "primaryKey": false,
          "notNull": true,
          "autoincrement": false,
          "default": "'email'"
        },
        "sender": {
          "name": "sender",
          "type": "text",
          "primaryKey": false,
          "notNull": false,
          "autoincrement": false
        },
        "kind": {
          "name": "kind",
          "type": "text",
          "primaryKey": false,
          "notNull": true,
          "autoincrement": false
        },
        "action": {
          "name": "action",
          "type": "text",
          "primaryKey": false,
          "notNull": true,
          "autoincrement": false
        },
        "created_at": {
          "name": "created_at",
          "type": "text",
          "primaryKey": false,
          "notNull": true,
          "autoincrement": false,
          "default": "(datetime('now'))"
        }
      },
      "indexes": {
        "uq_log_rules": {
          "name": "uq_log_rules",
          "columns": [
            "user_id",
            "source",
            "kind",
            "action"
          ],
          "isUnique": true
        }
      },
      "foreignKeys": {
        "log_rules_user_id_users_id_fk": {
          "name": "log_rules_user_id_users_id_fk",
          "tableFrom": "log_rules",
          "tableTo": "users",
          "columnsFrom": [
            "user_id"
          ],
          "columnsTo": [
            "id"
          ],
          "onDelete": "no action",
          "onUpdate": "no action"
        }
      },
      "compositePrimaryKeys": {},
      "uniqueConstraints": {},
      "checkConstraints": {
        "chk_log_rule_action": {
          "name": "chk_log_rule_action",
          "value": "action IN ('auto_approve','ignore')"
        }
      }
    },
    "log_whitelist": {
      "name": "log_whitelist",
      "columns": {
        "id": {
          "name": "id",
          "type": "integer",
          "primaryKey": true,
          "notNull": true,
          "autoincrement": false
        },
        "user_id": {
          "name": "user_id",
          "type": "integer",
          "primaryKey": false,
          "notNull": true,
          "autoincrement": false
        },
        "source": {
          "name": "source",
          "type": "text",
          "primaryKey": false,
          "notNull": true,
          "autoincrement": false,
          "default": "'email'"
        },
        "sender": {
          "name": "sender",
          "type": "text",
          "primaryKey": false,
          "notNull": true,
          "autoincrement": false
        },
        "enabled": {
          "name": "enabled",
          "type": "integer",
          "primaryKey": false,
          "notNull": true,
          "autoincrement": false,
          "default": 1
        },
        "note": {
          "name": "note",
          "type": "text",
          "primaryKey": false,
          "notNull": false,
          "autoincrement": false
        },
        "created_at": {
          "name": "created_at",
          "type": "text",
          "primaryKey": false,
          "notNull": true,
          "autoincrement": false,
          "default": "(datetime('now'))"
        }
      },
      "indexes": {
        "uq_whitelist_user_source_sender": {
          "name": "uq_whitelist_user_source_sender",
          "columns": [
            "user_id",
            "source",
            "sender"
          ],
          "isUnique": true
        }
      },
      "foreignKeys": {
        "log_whitelist_user_id_users_id_fk": {
          "name": "log_whitelist_user_id_users_id_fk",
          "tableFrom": "log_whitelist",
          "tableTo": "users",
          "columnsFrom": [
            "user_id"
          ],
          "columnsTo": [
            "id"
          ],
          "onDelete": "no action",
          "onUpdate": "no action"
        }
      },
      "compositePrimaryKeys": {},
      "uniqueConstraints": {},
      "checkConstraints": {}
    },
    "sessions": {
      "name": "sessions",
      "columns": {
        "id": {
          "name": "id",
          "type": "text",
          "primaryKey": true,
          "notNull": true,
          "autoincrement": false
        },
        "user_id": {
          "name": "user_id",
          "type": "integer",
          "primaryKey": false,
          "notNull": true,
          "autoincrement": false
        },
        "expires_at": {
          "name": "expires_at",
          "type": "text",
          "primaryKey": false,
          "notNull": true,
          "autoincrement": false
        },
        "user_agent": {
          "name": "user_agent",
          "type": "text",
          "primaryKey": false,
          "notNull": false,
          "autoincrement": false
        },
        "ip_address": {
          "name": "ip_address",
          "type": "text",
          "primaryKey": false,
          "notNull": false,
          "autoincrement": false
        },
        "created_at": {
          "name": "created_at",
          "type": "text",
          "primaryKey": false,
          "notNull": true,
          "autoincrement": false,
          "default": "(datetime('now'))"
        }
      },
      "indexes": {
        "idx_sessions_user": {
          "name": "idx_sessions_user",
          "columns": [
            "user_id"
          ],
          "isUnique": false
        }
      },
      "foreignKeys": {
        "sessions_user_id_users_id_fk": {
          "name": "sessions_user_id_users_id_fk",
          "tableFrom": "sessions",
          "tableTo": "users",
          "columnsFrom": [
            "user_id"
          ],
          "columnsTo": [
            "id"
          ],
          "onDelete": "cascade",
          "onUpdate": "no action"
        }
      },
      "compositePrimaryKeys": {},
      "uniqueConstraints": {},
      "checkConstraints": {}
    },
    "transactions": {
      "name": "transactions",
      "columns": {
        "id": {
          "name": "id",
          "type": "integer",
          "primaryKey": true,
          "notNull": true,
          "autoincrement": false
        },
        "user_id": {
          "name": "user_id",
          "type": "integer",
          "primaryKey": false,
          "notNull": true,
          "autoincrement": false
        },
        "item": {
          "name": "item",
          "type": "text",
          "primaryKey": false,
          "notNull": true,
          "autoincrement": false
        },
        "amount_minor": {
          "name": "amount_minor",
          "type": "integer",
          "primaryKey": false,
          "notNull": true,
          "autoincrement": false
        },
        "currency": {
          "name": "currency",
          "type": "text",
          "primaryKey": false,
          "notNull": true,
          "autoincrement": false,
          "default": "'PHP'"
        },
        "occurred_at": {
          "name": "occurred_at",
          "type": "text",
          "primaryKey": false,
          "notNull": true,
          "autoincrement": false
        },
        "category_id": {
          "name": "category_id",
          "type": "integer",
          "primaryKey": false,
          "notNull": false,
          "autoincrement": false
        },
        "notes": {
          "name": "notes",
          "type": "text",
          "primaryKey": false,
          "notNull": false,
          "autoincrement": false
        },
        "source": {
          "name": "source",
          "type": "text",
          "primaryKey": false,
          "notNull": true,
          "autoincrement": false,
          "default": "'manual'"
        },
        "external_id": {
          "name": "external_id",
          "type": "text",
          "primaryKey": false,
          "notNull": false,
          "autoincrement": false
        },
        "created_at": {
          "name": "created_at",
          "type": "text",
          "primaryKey": false,
          "notNull": true,
          "autoincrement": false,
          "default": "(datetime('now'))"
        },
        "updated_at": {
          "name": "updated_at",
          "type": "text",
          "primaryKey": false,
          "notNull": true,
          "autoincrement": false,
          "default": "(datetime('now'))"
        }
      },
      "indexes": {
        "idx_tx_user_date": {
          "name": "idx_tx_user_date",
          "columns": [
            "user_id",
            "occurred_at"
          ],
          "isUnique": false
        },
        "idx_tx_user_cat": {
          "name": "idx_tx_user_cat",
          "columns": [
            "user_id",
            "category_id"
          ],
          "isUnique": false
        },
        "idx_tx_external": {
          "name": "idx_tx_external",
          "columns": [
            "user_id",
            "external_id"
          ],
          "isUnique": true,
          "where": "\"transactions\".\"external_id\" is not null"
        }
      },
      "foreignKeys": {
        "transactions_user_id_users_id_fk": {
          "name": "transactions_user_id_users_id_fk",
          "tableFrom": "transactions",
          "tableTo": "users",
          "columnsFrom": [
            "user_id"
          ],
          "columnsTo": [
            "id"
          ],
          "onDelete": "no action",
          "onUpdate": "no action"
        },
        "transactions_category_id_categories_id_fk": {
          "name": "transactions_category_id_categories_id_fk",
          "tableFrom": "transactions",
          "tableTo": "categories",
          "columnsFrom": [
            "category_id"
          ],
          "columnsTo": [
            "id"
          ],
          "onDelete": "no action",
          "onUpdate": "no action"
        }
      },
      "compositePrimaryKeys": {},
      "uniqueConstraints": {},
      "checkConstraints": {}
    },
    "users": {
      "name": "users",
      "columns": {
        "id": {
          "name": "id",
          "type": "integer",
          "primaryKey": true,
          "notNull": true,
          "autoincrement": false
        },
        "email": {
          "name": "email",
          "type": "text",
          "primaryKey": false,
          "notNull": true,
          "autoincrement": false
        },
        "password_hash": {
          "name": "password_hash",
          "type": "text",
          "primaryKey": false,
          "notNull": true,
          "autoincrement": false
        },
        "display_name": {
          "name": "display_name",
          "type": "text",
          "primaryKey": false,
          "notNull": false,
          "autoincrement": false
        },
        "avatar_path": {
          "name": "avatar_path",
          "type": "text",
          "primaryKey": false,
          "notNull": false,
          "autoincrement": false
        },
        "failed_attempts": {
          "name": "failed_attempts",
          "type": "integer",
          "primaryKey": false,
          "notNull": true,
          "autoincrement": false,
          "default": 0
        },
        "locked_until": {
          "name": "locked_until",
          "type": "text",
          "primaryKey": false,
          "notNull": false,
          "autoincrement": false
        },
        "created_at": {
          "name": "created_at",
          "type": "text",
          "primaryKey": false,
          "notNull": true,
          "autoincrement": false,
          "default": "(datetime('now'))"
        },
        "updated_at": {
          "name": "updated_at",
          "type": "text",
          "primaryKey": false,
          "notNull": true,
          "autoincrement": false,
          "default": "(datetime('now'))"
        }
      },
      "indexes": {
        "users_email_unique": {
          "name": "users_email_unique",
          "columns": [
            "email"
          ],
          "isUnique": true
        }
      },
      "foreignKeys": {},
      "compositePrimaryKeys": {},
      "uniqueConstraints": {},
      "checkConstraints": {}
    }
  },
  "views": {},
  "enums": {},
  "_meta": {
    "schemas": {},
    "tables": {},
    "columns": {}
  },
  "internal": {
    "indexes": {}
  }
}